README.rst
setup.py
jusolink/__init__.py
jusolink/jusolink.py
jusolink.egg-info/PKG-INFO
jusolink.egg-info/SOURCES.txt
jusolink.egg-info/dependency_links.txt
jusolink.egg-info/pbr.json
jusolink.egg-info/requires.txt
jusolink.egg-info/top_level.txt