Metadata-Version: 1.1
Name: jusolink
Version: 1.0.3
Summary: Jusolink API SDK Library
Home-page: https://github.com/linkhub-sdk/Jusolink.py
Author: Jeong Yohan
Author-email: yhjeong@linkhub.co.kr
License: MIT
Download-URL: https://github.com/linkhub-sdk/Jusolink.py/archive/1.0.3.tar.gz
Platform: Posix; MacOS X; Windows
Classifier: Development Status :: 5 - Production/Stable
Classifier: Intended Audience :: Developers
Classifier: License :: OSI Approved :: MIT License
Classifier: Operating System :: OS Independent
Classifier: Topic :: Internet
Classifier: Programming Language :: Python :: 2
Classifier: Programming Language :: Python :: 2.6
Classifier: Programming Language :: Python :: 2.7
Classifier: Programming Language :: Python :: 3
Classifier: Programming Language :: Python :: 3.3
Classifier: Programming Language :: Python :: 3.4
